LICENSE
MANIFEST.in
README.md
setup.py
pysendy/__init__.py
pysendy/exceptions.py
pysendy/pysendy.py
pysendy.egg-info/PKG-INFO
pysendy.egg-info/SOURCES.txt
pysendy.egg-info/dependency_links.txt
pysendy.egg-info/requires.txt
pysendy.egg-info/top_level.txt
pysendy.egg-info/zip-safe