Metadata-Version: 1.1
Name: pysendy
Version: 0.0.2
Summary: Sendy API v1.1.7 for Python.
Home-page: https://github.com/thiagofa/pysendy
Author: Thiago Faria de Andrade
Author-email: thiagofa@gmail.com
License: UNKNOWN
Download-URL: http://pypi.python.org/pypi/pysendy/
Keywords: pysendy sendy sendy.co wrapper api
Platform: UNKNOWN
Classifier: Development Status :: 5 - Production/Stable
Classifier: Intended Audience :: Developers
Classifier: License :: OSI Approved :: MIT License
Classifier: Natural Language :: English
Classifier: Operating System :: OS Independent
Classifier: Programming Language :: Python
Classifier: Topic :: Software Development :: Libraries :: Python Modules
